{"wCNQ389PCTsZOkv6+8Lucg==":"1-797x285.jpg","swyNZ+2zH/A+RXAxdUFlJA==":"1-600x214.jpg","cx35IFmRLPdT/HIo3ptQ3Q==":"2-600x209.jpg","nSEvC5ioLMmpD2x5/tABNA==":"3-600x183.jpg","nfRH4Z0oTn9f1tPRZksVdQ==":"4-600x237.jpg","BFLQEZNQH7V9C4K5AL5d8w==":"5-600x216.jpg","yHmonTojiozRTWyOh65fkQ==":"6-600x220.jpg","o6ICtHfgnPI4I/zcfQdZ6Q==":"1-1-600x214.jpg","/sgELfilIQkf2WT/X4Io/A==":"2-1-600x209.jpg","sxPvmSNgsAe9k7Rq9IUWdA==":"3-1-600x183.jpg","oL1h2d+WM8dl0vOfl0OZGg==":"4-1-600x237.jpg","o3QZLO7DDdfqvYd36/dkDQ==":"1-2-797x285.jpg","dD6F4N+EC415+9NduSk+FQ==":"2-797x278.jpg","l12BqI/LFmMGH0ZRWopXsg==":"1-4-797x285.jpg","B6EeogpwTFqXwIL5MlFtAg==":"2-1-797x278.jpg","akQAJMo97edbSg3GyJyMxw==":"3-800x244.jpg","7QYOKmCcNu1kXf9DPYkZ9Q==":"4-800x316.jpg","3brgK5dNTZDS7ElBkWkyRw==":"5-800x289.jpg","nuB9clwpF1ErxKkXAVCxsA==":"1-4-797x285-428x272.jpg","hMgSGtb/4pNIl9L19bE99w==":"4-800x316-432x316.jpg","OK2OURa5BCuTXK2rkEzwkw==":"6-800x294.jpg"}